sinode/__init__.py
sinode/sinode.py
sinode-1.1.2.dist-info/LICENSE
sinode-1.1.2.dist-info/METADATA
sinode-1.1.2.dist-info/WHEEL
sinode-1.1.2.dist-info/top_level.txt
sinode-1.1.2.dist-info/RECORD
