Metadata-Version: 2.1
Name: sinode
Version: 1.1.2
Summary: An inheritable Node class
Home-page: https://github.com/julianfl0w/sinode
Author: Julian Loiacono
Author-email: jcloiacon@gmail.com
License: UNKNOWN
Platform: UNKNOWN
